sqlitedict.py
sqlitedict-1.4.0.dist-info/DESCRIPTION.rst
sqlitedict-1.4.0.dist-info/METADATA
sqlitedict-1.4.0.dist-info/metadata.json
sqlitedict-1.4.0.dist-info/pbr.json
sqlitedict-1.4.0.dist-info/RECORD
sqlitedict-1.4.0.dist-info/top_level.txt
sqlitedict-1.4.0.dist-info/WHEEL
