Metadata-Version: 1.1
Name: sqlitedict
Version: 1.4.0
Summary: Persistent dict in Python, backed up by sqlite3 and pickle, multithread-safe.
Home-page: https://github.com/piskvorky/sqlitedict
Author: Radim Rehurek
Author-email: me@radimrehurek.com
License: Apache 2.0
Download-URL: http://pypi.python.org/pypi/sqlitedict
Keywords: sqlite,persistent dict,multithreaded
Platform: any
Classifier: Development Status :: 5 - Production/Stable
Classifier: Environment :: Console
Classifier: Intended Audience :: Developers
Classifier: License :: OSI Approved :: Apache Software License
Classifier: Operating System :: OS Independent
Classifier: Programming Language :: Python :: 2.5
Classifier: Programming Language :: Python :: 2.6
Classifier: Programming Language :: Python :: 2.7
Classifier: Programming Language :: Python :: 3.3
Classifier: Programming Language :: Python :: 3.4
Classifier: Topic :: Database :: Front-Ends
